gfloat/__init__.py
gfloat/block.py
gfloat/decode.py
gfloat/decode_ndarray.py
gfloat/encode.py
gfloat/encode_ndarray.py
gfloat/formats.py
gfloat/printing.py
gfloat/round.py
gfloat/round_ndarray.py
gfloat/types.py
gfloat-0.5.2.dist-info/licenses/LICENSE
gfloat-0.5.2.dist-info/METADATA
gfloat-0.5.2.dist-info/WHEEL
gfloat-0.5.2.dist-info/top_level.txt
gfloat-0.5.2.dist-info/RECORD
