Metadata-Version: 2.4
Name: gfloat
Version: 0.5.2
Summary: Generic floating point handling in Python
Author-email: Andrew Fitzgibbon <awf@fitzgibbon.ie>
Classifier: Intended Audience :: Developers
Classifier: License :: OSI Approved :: MIT License
Classifier: Programming Language :: Python :: 3
Classifier: Development Status :: 3 - Alpha
Requires-Python: >=3.8.1
License-File: LICENSE
Requires-Dist: numpy
Requires-Dist: more_itertools
Requires-Dist: array-api-compat
Provides-Extra: dev
Requires-Dist: pytest; extra == "dev"
Requires-Dist: nbval; extra == "dev"
Requires-Dist: ml_dtypes; extra == "dev"
Requires-Dist: jaxlib; extra == "dev"
Requires-Dist: jax; extra == "dev"
Requires-Dist: torch; extra == "dev"
Requires-Dist: array-api-strict; extra == "dev"
Requires-Dist: torchao==0.10; extra == "dev"
Requires-Dist: airium; extra == "dev"
Requires-Dist: pandas; extra == "dev"
Requires-Dist: matplotlib; extra == "dev"
Requires-Dist: pre-commit; extra == "dev"
Requires-Dist: black; extra == "dev"
Requires-Dist: mypy; extra == "dev"
Requires-Dist: black[jupyter]; extra == "dev"
Requires-Dist: isort; extra == "dev"
Requires-Dist: sphinx==7.1.2; extra == "dev"
Requires-Dist: sphinx-rtd-theme==1.3.0rc1; extra == "dev"
Requires-Dist: sphinx_paramlinks; extra == "dev"
Requires-Dist: myst_nb; extra == "dev"
Dynamic: license-file
